[
  {
    "id": "mepddnqj",
    "createdAt": "2025-08-24T07:31:29.515Z",
    "title": "管理员测试",
    "desc": "管理员测试",
    "category": "study",
    "images": [],
    "authorEmail": "admin1@qq.com",
    "authorName": "admin1",
    "authorAvatar": ""
  },
  {
    "id": "mepcvxju",
    "createdAt": "2025-08-24T07:17:42.427Z",
    "title": "置顶测试",
    "desc": "置顶测试",
    "category": "life",
    "images": [],
    "authorEmail": "a@123.com",
    "authorName": "Li",
    "authorAvatar": "/uploads/1755432571769-31f051b9aa9408.jpg",
    "pinned": false
  },
  {
    "id": "megxwya5",
    "createdAt": "2025-08-18T09:56:26.381Z",
    "title": "撒打算你打开是你打开你大姐你姐夫",
    "desc": "啊是看你的空间安抚肌肤的健身房",
    "category": "life",
    "images": [
      "/uploads/1755510986378-12696695a26b18.jpg"
    ],
    "authorEmail": "kk@123.com",
    "authorName": "kk",
    "authorAvatar": "data:image/svg+xml;utf8,%3Csvg%20xmlns%3D%22http%3A%2F%2Fwww.w3.org%2F2000%2Fsvg%22%20width%3D%22128%22%20height%3D%22128%22%3E%3Crect%20width%3D%22100%25%22%20height%3D%22100%25%22%20fill%3D%22%23e5e7eb%22%2F%3E%3Ccircle%20cx%3D%2264%22%20cy%3D%2254%22%20r%3D%2226%22%20fill%3D%22%23cbd5e1%22%2F%3E%3Crect%20x%3D%2224%22%20y%3D%2286%22%20width%3D%2280%22%20height%3D%2228%22%20rx%3D%2214%22%20fill%3D%22%23cbd5e1%22%2F%3E%3C%2Fsvg%3E",
    "pinned": true,
    "pinnedAt": "2025-01-27T10:00:00.000Z"
  },
  {
    "id": "megxwfsk",
    "createdAt": "2025-08-18T09:56:02.420Z",
    "title": "asdjaksdnaknsd",
    "desc": "fknsjfnkas",
    "category": "life",
    "images": [
      "/uploads/1755510962415-f9912ab0bc68a8.jpg"
    ],
    "authorEmail": "kk@123.com",
    "authorName": "kk",
    "authorAvatar": "data:image/svg+xml;utf8,%3Csvg%20xmlns%3D%22http%3A%2F%2Fwww.w3.org%2F2000%2Fsvg%22%20width%3D%22128%22%20height%3D%22128%22%3E%3Crect%20width%3D%22100%25%22%20height%3D%22100%25%22%20fill%3D%22%23e5e7eb%22%2F%3E%3Ccircle%20cx%3D%2264%22%20cy%3D%2254%22%20r%3D%2226%22%20fill%3D%22%23cbd5e1%22%2F%3E%3Crect%20x%3D%2224%22%20y%3D%2286%22%20width%3D%2280%22%20height%3D%2228%22%20rx%3D%2214%22%20fill%3D%22%23cbd5e1%22%2F%3E%3C%2Fsvg%3E"
  },
  {
    "id": "megxdx5t",
    "createdAt": "2025-08-18T09:41:38.465Z",
    "title": "",
    "desc": "123123123123123131321",
    "category": "fun",
    "images": [],
    "authorEmail": "kk@123.com",
    "authorName": "kk",
    "authorAvatar": "data:image/svg+xml;utf8,%3Csvg%20xmlns%3D%22http%3A%2F%2Fwww.w3.org%2F2000%2Fsvg%22%20width%3D%22128%22%20height%3D%22128%22%3E%3Crect%20width%3D%22100%25%22%20height%3D%22100%25%22%20fill%3D%22%23e5e7eb%22%2F%3E%3Ccircle%20cx%3D%2264%22%20cy%3D%2254%22%20r%3D%2226%22%20fill%3D%22%23cbd5e1%22%2F%3E%3Crect%20x%3D%2224%22%20y%3D%2286%22%20width%3D%2280%22%20height%3D%2228%22%20rx%3D%2214%22%20fill%3D%22%23cbd5e1%22%2F%3E%3C%2Fsvg%3E"
  },
  {
    "id": "megu3ds1",
    "createdAt": "2025-08-18T08:09:27.937Z",
    "title": "",
    "desc": "12312312技能可被看见 ",
    "category": "share",
    "images": [
      "/uploads/1755504567933-6f704b16bbaab8.jpg"
    ],
    "authorEmail": "l@123.com",
    "authorName": "oo",
    "authorAvatar": "/uploads/1755416553774-76802b02dee398.JPG"
  },
  {
    "id": "megu2vpr",
    "createdAt": "2025-08-18T08:09:04.527Z",
    "title": "",
    "desc": "123123123123123jhkjbk",
    "category": "life",
    "images": [],
    "authorEmail": "l@123.com",
    "authorName": "oo",
    "authorAvatar": "/uploads/1755416553774-76802b02dee398.JPG"
  },
  {
    "id": "megu2gv8",
    "createdAt": "2025-08-18T08:08:45.284Z",
    "title": "",
    "desc": "1231231231231231",
    "category": "share",
    "images": [],
    "authorEmail": "l@123.com",
    "authorName": "oo",
    "authorAvatar": "/uploads/1755416553774-76802b02dee398.JPG"
  },
  {
    "id": "megu2aib",
    "createdAt": "2025-08-18T08:08:37.043Z",
    "title": "",
    "desc": "12312312312312312",
    "category": "life",
    "images": [],
    "authorEmail": "l@123.com",
    "authorName": "oo",
    "authorAvatar": "/uploads/1755416553774-76802b02dee398.JPG"
  },
  {
    "id": "megu25ni",
    "createdAt": "2025-08-18T08:08:30.750Z",
    "title": "123",
    "desc": "123",
    "category": "share",
    "images": [],
    "authorEmail": "l@123.com",
    "authorName": "oo",
    "authorAvatar": "/uploads/1755416553774-76802b02dee398.JPG"
  },
  {
    "id": "meflkdr4",
    "createdAt": "2025-08-17T11:22:58.336Z",
    "title": "我爱你",
    "desc": "Iloveyou",
    "category": "share",
    "images": [
      "/uploads/1755429778332-2c0671ee647f08.jpg"
    ],
    "authorEmail": "a@123.com",
    "authorName": "Li",
    "authorAvatar": "/uploads/1755416347809-5bf59c103b1858.JPG"
  },
  {
    "id": "meflifdr",
    "createdAt": "2025-08-17T11:21:27.135Z",
    "title": "123",
    "desc": "123",
    "category": "life",
    "images": [
      "/uploads/1755429687127-7985a9cb81801.jpg"
    ],
    "authorEmail": "l@123.com",
    "authorName": "oo",
    "authorAvatar": "/uploads/1755416553774-76802b02dee398.JPG"
  },
  {
    "id": "meffpqw1",
    "createdAt": "2025-08-17T08:39:10.945Z",
    "title": "123",
    "desc": "123",
    "images": [
      "/uploads/1755419950935-bb85a7e714219.jpg"
    ]
  },
  {
    "id": "meffq4i9",
    "createdAt": "2025-08-17T08:39:28.593Z",
    "title": "a s d",
    "desc": "a s d",
    "images": [
      "/uploads/1755419968591-9927877c428a2.jpg"
    ]
  },
  {
    "id": "meffwby7",
    "createdAt": "2025-08-17T08:44:18.175Z",
    "title": "asd",
    "desc": "asd",
    "images": [
      "/uploads/1755420258171-cf11afdb673c68.jpg"
    ]
  },
  {
    "id": "meffwmax",
    "createdAt": "2025-08-17T08:44:31.593Z",
    "title": "lss",
    "desc": "das",
    "images": [
      "/uploads/1755420271591-02ac4ea9349a48.jpg"
    ]
  },
  {
    "id": "mefl1lfg",
    "createdAt": "2025-08-17T11:08:21.820Z",
    "title": "123",
    "desc": "123",
    "images": [
      "/uploads/1755428901818-12ca65ddc6c67.jpg"
    ]
  }
]